{
  "5min": {
    "name": "5分钟事件合约",
    "initial_balance": 1000,
    "current_balance": 1085,
    "trade_history": [
      {
        "type": "close",
        "direction": "short",
        "price": 66043,
        "entry_price": 66128,
        "exit_price": 66043,
        "amount": 100,
        "timestamp": "2026-03-02T19:41:10",
        "result": "profit",
        "profit": 85
      }
    ],
    "active_position": null,
    "daily_stats": {
      "2026-03-02": {
        "trades": 1,
        "wins": 1,
        "losses": 0,
        "profit": 85,
        "win_rate": 100
      }
    }
  },
  "30min": {
    "name": "30分钟固定周期",
    "initial_balance": 1000,
    "current_balance": 1285.0,
    "trade_history": [
      {
        "type": "close",
        "direction": "long",
        "price": 66242.5,
        "entry_price": 66142.5,
        "exit_price": 66242.5,
        "amount": 100,
        "timestamp": "2026-03-02T19:41:10",
        "result": "profit",
        "profit": 100
      },
      {
        "type": "open",
        "direction": "long",
        "price": 69288.0,
        "amount": 100,
        "timestamp": "2026-03-03T01:13:14.788969",
        "signal_strength": 5
      },
      {
        "type": "close",
        "direction": "long",
        "entry_price": 69288.0,
        "exit_price": 70673.76,
        "result": "profit",
        "profit": 85.0,
        "timestamp": "2026-03-03T17:41:22.030283",
        "amount": 100
      }
    ],
    "daily_stats": {
      "2026-03-02": {
        "trades": 1,
        "wins": 1,
        "losses": 0,
        "profit": 100,
        "win_rate": 100
      }
    }
  },
  "signals_history": [],
  "ai_models": [
    {
      "id": "kimi-coding-v2.5",
      "name": "Kimi-Coding-v2.5",
      "type": "多周期技术分析",
      "description": "基于多时间框架的技术分析模型",
      "accuracy": 62.5,
      "total_signals": 8,
      "win_signals": 5,
      "loss_signals": 3
    }
  ],
  "ai_analysis": {
    "current_model": "kimi-coding-v2.5",
    "current_trend": {
      "4H": "bullish",
      "30M": "bullish",
      "15M": "neutral",
      "overall": "看涨"
    },
    "key_levels": {
      "support": [
        66000,
        65500,
        65000
      ],
      "resistance": [
        66500,
        67000,
        67500
      ]
    },
    "indicators": {
      "RSI_4H": 62.5,
      "RSI_30M": 58.3,
      "RSI_15M": 45.2,
      "MACD_4H": "bullish",
      "MACD_30M": "bullish",
      "BB_position": "中轨附近"
    },
    "model_prediction": {
      "next_1h": {
        "up": 65,
        "down": 35
      },
      "confidence": 0.68,
      "suggested_action": "轻仓做多"
    },
    "last_updated": "2026-03-02T23:02:18.766762"
  },
  "performance": {
    "total_trades": 2,
    "total_wins": 2,
    "total_losses": 0,
    "overall_win_rate": 100,
    "total_profit": 185,
    "best_trade": 100,
    "worst_trade": 85
  },
  "_last_updated": "2026-03-03T18:27:03.650129",
  "_sync_version": "3.0",
  "_data_integrity": "fixed"
}